__init__.py
arg_parser.py
clidir.py
command_loader.py
help.py
clidir-0.1.2.dist-info/LICENSE
clidir-0.1.2.dist-info/METADATA
clidir-0.1.2.dist-info/WHEEL
clidir-0.1.2.dist-info/top_level.txt
clidir-0.1.2.dist-info/RECORD
