Metadata-Version: 2.1
Name: clidir
Version: 0.1.2
Summary: A tiny Python library to easily create CLI applications with sub commands
Author: Isaac Benitez
Project-URL: Homepage, https://github.com/isacben/clidir
Classifier: Programming Language :: Python :: 3
Classifier: License :: OSI Approved :: MIT License
Classifier: Operating System :: OS Independent
Requires-Python: >=3.8
License-File: LICENSE
Provides-Extra: test
Requires-Dist: pytest ; extra == 'test'
